sthenelus/__init__.py
sthenelus/sthenelus.py
sthenelus-0.1.0.dist-info/DESCRIPTION.rst
sthenelus-0.1.0.dist-info/METADATA
sthenelus-0.1.0.dist-info/RECORD
sthenelus-0.1.0.dist-info/WHEEL
sthenelus-0.1.0.dist-info/metadata.json
sthenelus-0.1.0.dist-info/top_level.txt
