Metadata-Version: 2.0
Name: sthenelus
Version: 0.1.0
Summary: Sthenelus Distributed Task Queue Client
Home-page: http://www.play-consult.co.uk
Author: Alastair McFarlane
Author-email: alastair@play-consult.co.uk
License: MIT
Platform: any
Classifier: Development Status :: 4 - Beta
Classifier: License :: OSI Approved :: MIT License
Classifier: Topic :: System :: Distributed Computing
Classifier: Topic :: Software Development :: Object Brokering
Classifier: Programming Language :: Python
Classifier: Programming Language :: Python :: 3
Classifier: Programming Language :: Python :: 3.4
Classifier: Programming Language :: Python :: 3.5
Classifier: Operating System :: OS Independent
Requires-Dist: boto3 (>=1.3.1)
